addendum/__init__.py
addendum/admin.py
addendum/apps.py
addendum/forms.py
addendum/models.py
addendum/management/__init__.py
addendum/management/commands/__init__.py
addendum/management/commands/refresh_snippet_cache.py
addendum/migrations/0001_initial.py
addendum/migrations/0002_auto_translations.py
addendum/migrations/__init__.py
addendum/templatetags/__init__.py
addendum/templatetags/addendum_tags.py
django_addendum-0.6.0.dist-info/AUTHORS.rst
django_addendum-0.6.0.dist-info/LICENSE
django_addendum-0.6.0.dist-info/METADATA
django_addendum-0.6.0.dist-info/WHEEL
django_addendum-0.6.0.dist-info/top_level.txt
django_addendum-0.6.0.dist-info/RECORD
