Metadata-Version: 2.1
Name: django-addendum
Version: 0.6.0
Summary: Simple template-based content swapping for CMS-less sites
Home-page: https://github.com/bennylope/django-addendum
Author: Ben Lopatin
Author-email: ben.lopatin@wellfireinteractive.com
License: BSD License
Platform: OS Independent
Classifier: Development Status :: 4 - Beta
Classifier: Environment :: Web Environment
Classifier: Intended Audience :: Developers
Classifier: License :: OSI Approved :: BSD License
Classifier: Operating System :: OS Independent
Classifier: Programming Language :: Python
Classifier: Programming Language :: Python :: 2.7
Classifier: Programming Language :: Python :: 3.3
Classifier: Programming Language :: Python :: 3.4
Classifier: Framework :: Django
